tree_sitter_requirements/__init__.py
tree_sitter_requirements/__init__.pyi
tree_sitter_requirements/_binding.abi3.so
tree_sitter_requirements/binding.c
tree_sitter_requirements/py.typed
tree_sitter_requirements/queries/highlights.scm
tree_sitter_requirements-0.5.0.dist-info/METADATA
tree_sitter_requirements-0.5.0.dist-info/WHEEL
tree_sitter_requirements-0.5.0.dist-info/top_level.txt
tree_sitter_requirements-0.5.0.dist-info/RECORD
tree_sitter_requirements-0.5.0.dist-info/licenses/LICENSE
