Metadata-Version: 2.4
Name: tree-sitter-requirements
Version: 0.5.0
Summary: pip requirements grammar for tree-sitter
Author-email: ObserverOfTime <chronobserver@disroot.org>
License: MIT
Project-URL: Homepage, https://github.com/tree-sitter-grammars/tree-sitter-requirements
Project-URL: Issues, https://github.com/tree-sitter-grammars/tree-sitter-requirements/issues
Project-URL: Sponsor, https://github.com/sponsors/ObserverOfTime
Keywords: incremental,parsing,tree-sitter,requirements
Classifier: Intended Audience :: Developers
Classifier: License :: OSI Approved :: MIT License
Classifier: Topic :: Software Development :: Compilers
Classifier: Topic :: Text Processing :: Linguistic
Classifier: Typing :: Typed
Requires-Python: >=3.10
License-File: LICENSE
Provides-Extra: core
Requires-Dist: tree-sitter~=0.24; extra == "core"
Dynamic: license-file
